{
  "name": "Apartament",
  "plural": "Apartaments",
  "base": "PersistedModel",
  "idInjection": true,
  "options": {
    "validateUpsert": true
  },
  "properties": {
    "name": {
      "type": "string",
      "required": true
    },
    "type": {
      "type": "string",
      "required": true
    },
    "value": {
      "type": "number",
      "required": true
    },
    "idUSer": {
      "type": "number",
      "required": true
    },
    "area": {
      "type": "number",
      "required": true
    },
    "description": {
      "type": "string",
      "required": true
    },
    "location": {
      "type": "string",
      "required": true
    },
    "numRooms": {
      "type": "number",
      "required": true
    }
  },
  "validations": [],
  "relations": {},
  "acls": [],
  "methods": {}
}
